streamsets/testframework/__init__.py
streamsets/testframework/__version__.py
streamsets/testframework/cli/__init__.py
streamsets/testframework/cli/build.py
streamsets/testframework/cli/generate_test_stub.py
streamsets/testframework/cli/info.py
streamsets/testframework/cli/run_profile_manager.py
streamsets/testframework/cli/start_sdc.py
streamsets/testframework/cli/start_st.py
streamsets_testframework-4.0.0.dist-info/METADATA
streamsets_testframework-4.0.0.dist-info/NOTICE.txt
streamsets_testframework-4.0.0.dist-info/WHEEL
streamsets_testframework-4.0.0.dist-info/entry_points.txt
streamsets_testframework-4.0.0.dist-info/top_level.txt
streamsets_testframework-4.0.0.dist-info/RECORD
